mercado_pago/__init__.py
mercado_pago/models.py
mercado_pago/serializers.py
mercado_pago/services.py
mercado_pago/urls.py
mercado_pago/views.py
django_mercadopago_integration-0.1.0.dist-info/LICENSE
django_mercadopago_integration-0.1.0.dist-info/METADATA
django_mercadopago_integration-0.1.0.dist-info/WHEEL
django_mercadopago_integration-0.1.0.dist-info/RECORD
