Metadata-Version: 2.3
Name: django-mercadopago-integration
Version: 0.1.0
Summary: Reusable Mercado Pago integration for Django projects
License: MIT
Author: Crhistyan Silva
Author-email: crhistyan.silva@falcode.dev
Requires-Python: >=3.8,<4.0
Classifier: License :: OSI Approved :: MIT License
Classifier: Programming Language :: Python :: 3
Classifier: Programming Language :: Python :: 3.8
Classifier: Programming Language :: Python :: 3.9
Classifier: Programming Language :: Python :: 3.10
Classifier: Programming Language :: Python :: 3.11
Classifier: Programming Language :: Python :: 3.12
Classifier: Programming Language :: Python :: 3.13
Requires-Dist: django (>=3.2)
Requires-Dist: djangorestframework
Requires-Dist: requests
